pygenderbr
