Metadata-Version: 1.1
Name: pygenderbr
Version: 0.5.0
Summary: Python tool to interface with "Nomes" IBGE API v.2
Home-page: https://github.com/alexfurtunatoifrn/pygenderbr
Author: Alex Furtunato
Author-email: alexfurtunato@gmail.com
License: MIT
Keywords: gender names brazil ibge
Platform: UNKNOWN
Classifier: Development Status :: 3 - Alpha
Classifier: Topic :: Software Development :: Build Tools
Classifier: Topic :: Software Development :: Libraries :: Python Modules
Classifier: Topic :: Scientific/Engineering
Classifier: License :: OSI Approved :: MIT License
Classifier: Programming Language :: Python :: 3
